b3/__init__.py
b3/composite_dynamic.py
b3/composite_schema.py
b3/datatypes.py
b3/guess_type.py
b3/hexdump.py
b3/item.py
b3/type_basic.py
b3/type_codecs.py
b3/type_decimal.py
b3/type_sched.py
b3/type_varint.py
b3/utils.py
b3/tests/__init__.py
b3/tests/examples.py
b3/tests/test_comp_dynamic.py
b3/tests/test_comp_schema.py
b3/tests/test_core.py
b3/tests/test_decimal.py
b3/tests/test_item_header.py
b3/tests/test_sched.py
b3/tests/test_utils.py
b3/tests/test_varint.py
b3buf-1.0.11.data/data/LICENSE.txt
b3buf-1.0.11.dist-info/AUTHORS
b3buf-1.0.11.dist-info/LICENSE.txt
b3buf-1.0.11.dist-info/METADATA
b3buf-1.0.11.dist-info/WHEEL
b3buf-1.0.11.dist-info/top_level.txt
b3buf-1.0.11.dist-info/RECORD
