Metadata-Version: 2.1
Name: b3buf
Version: 1.0.11
Summary: B3 is a binary serializer which is easy like json, compact like msgpack, powerful like protobuf, and handles datetimes in python
Home-page: https://github.com/oddy/b3
Author: Beau Butler
Author-email: beau.butler@gmail.com
License: MIT
Platform: UNKNOWN
Classifier: License :: OSI Approved :: MIT License
Classifier: Programming Language :: Python :: 2.7
Classifier: Programming Language :: Python :: 3
Classifier: Development Status :: 5 - Production/Stable
License-File: LICENSE.txt
License-File: AUTHORS
Requires-Dist: six
